bnlp/__init__.py
bnlp/cleantext/__init__.py
bnlp/cleantext/clean.py
bnlp/cleantext/constants.py
bnlp/cli/__init__.py
bnlp/cli/main.py
bnlp/core/__init__.py
bnlp/core/async_loader.py
bnlp/core/batch.py
bnlp/core/exceptions.py
bnlp/core/pipeline.py
bnlp/core/protocols.py
bnlp/corpus/__init__.py
bnlp/corpus/_stopwords.py
bnlp/corpus/corpus.py
bnlp/embedding/__init__.py
bnlp/embedding/doc2vec.py
bnlp/embedding/fasttext.py
bnlp/embedding/glove.py
bnlp/embedding/word2vec.py
bnlp/langdetect/__init__.py
bnlp/langdetect/detector.py
bnlp/spellcheck/__init__.py
bnlp/spellcheck/spellchecker.py
bnlp/token_classification/__init__.py
bnlp/token_classification/ner.py
bnlp/token_classification/pos.py
bnlp/token_classification/token_classification_trainer.py
bnlp/tokenizer/__init__.py
bnlp/tokenizer/basic.py
bnlp/tokenizer/nltk.py
bnlp/tokenizer/sentencepiece.py
bnlp/utils/__init__.py
bnlp/utils/config.py
bnlp/utils/downloader.py
bnlp/utils/utils.py
bnlp_toolkit-4.4.0.dist-info/licenses/LICENSE
bnlp_toolkit-4.4.0.dist-info/METADATA
bnlp_toolkit-4.4.0.dist-info/WHEEL
bnlp_toolkit-4.4.0.dist-info/entry_points.txt
bnlp_toolkit-4.4.0.dist-info/top_level.txt
bnlp_toolkit-4.4.0.dist-info/RECORD
