Metadata-Version: 2.4
Name: bnlp_toolkit
Version: 4.4.0
Summary: BNLP is a natural language processing toolkit for Bengali Language
Home-page: https://github.com/sagorbrur/bnlp
Author: Sagor Sarker
Author-email: sagorhem3532@gmail.com
License: MIT
Classifier: Programming Language :: Python :: 3
Classifier: License :: OSI Approved :: MIT License
Classifier: Operating System :: OS Independent
Requires-Python: >=3.6
License-File: LICENSE
Requires-Dist: sentencepiece==0.2.0
Requires-Dist: gensim==4.3.2
Requires-Dist: nltk
Requires-Dist: numpy
Requires-Dist: scipy==1.10.1
Requires-Dist: sklearn-crfsuite==0.3.6
Requires-Dist: tqdm==4.66.3
Requires-Dist: ftfy==6.2.0
Requires-Dist: emoji==1.7.0
Requires-Dist: requests
Requires-Dist: symspellpy>=6.7.0
Provides-Extra: fasttext
Requires-Dist: fasttext>=0.9.2; extra == "fasttext"
Provides-Extra: spellcheck
Requires-Dist: symspellpy>=6.7.0; extra == "spellcheck"
Provides-Extra: langdetect
Requires-Dist: fasttext>=0.9.2; extra == "langdetect"
Provides-Extra: all
Requires-Dist: symspellpy>=6.7.0; extra == "all"
Requires-Dist: fasttext>=0.9.2; extra == "all"
Dynamic: author
Dynamic: author-email
Dynamic: classifier
Dynamic: description
Dynamic: description-content-type
Dynamic: home-page
Dynamic: license
Dynamic: license-file
Dynamic: provides-extra
Dynamic: requires-dist
Dynamic: requires-python
Dynamic: summary
